[
    {
      "title": "Oportunidades de estágio",
      "href": "https://chat.whatsapp.com/IpbibLVw00pC8CuHSRhnFD",
      "icon": "https://www.lg.com.br/lps/wp-content/uploads/2020/10/Estagiario3.png"
    },
    {
        "title": "Dasi",
        "href": "https://chat.whatsapp.com/G9izoMp3hop4HncsYRfAYw",
        "icon": "https://instagram.fvdc1-1.fna.fbcdn.net/v/t51.2885-19/s150x150/141870827_1300413596981043_1935560621615143423_n.jpg?tp=1&_nc_ht=instagram.fvdc1-1.fna.fbcdn.net&_nc_ohc=UVsDxdAF728AX92yIAb&oh=e7a1710e5dedd2f178691f3194da8e00&oe=6073D713"
    },
    {
        "title": "Protocolo do IFBA",
        "href": "https://api.whatsapp.com/send?phone=557734263355&text=Ol%C3%A1%2C%20sou%20aluno%20de%20BSI.%20Gostaria%20de%20gerar%20um%20protocolo.",
        "icon": "https://www.tce.sp.gov.br/sites/default/files/inline-images/playstore-icon_sem_fundo.png"
    }
]